bottle_elastic_apm/__init__.py
bottle_elastic_apm/tracer.py
bottle_elastic_apm/utils.py
bottle_elastic_apm-0.1.1.dist-info/LICENSE
bottle_elastic_apm-0.1.1.dist-info/METADATA
bottle_elastic_apm-0.1.1.dist-info/WHEEL
bottle_elastic_apm-0.1.1.dist-info/top_level.txt
bottle_elastic_apm-0.1.1.dist-info/RECORD
