Metadata-Version: 2.1
Name: bottle-elastic-apm
Version: 0.1.1
Summary: Plugin to implement instrumentation of elastic apm on a bottle server.
Home-page: https://gitlab.com/TruckPad/utils/bottle-elastic-apm
Author: TruckPad Dev Team
Author-email: devs@truckpad.com.br
License: UNKNOWN
Platform: UNKNOWN
Classifier: Development Status :: 2 - Pre-Alpha
Classifier: Operating System :: POSIX
Classifier: Programming Language :: Python :: 3
Classifier: Topic :: Internet :: WWW/HTTP
License-File: LICENSE
Requires-Dist: bottle
Requires-Dist: elastic-apm
